toolbox/__init__.py
toolbox/django/__init__.py
toolbox/django/rest/__init__.py
toolbox/django/rest/authentication/__init__.py
toolbox/django/rest/authentication/slack.py
toolbox/flask/__init__.py
toolbox/flask/authentication/__init__.py
toolbox/flask/authentication/slack.py
toolbox/slack/__init__.py
toolbox/slack/verify.py
politico_toolbox-0.0.8.dist-info/LICENSE
politico_toolbox-0.0.8.dist-info/METADATA
politico_toolbox-0.0.8.dist-info/WHEEL
politico_toolbox-0.0.8.dist-info/top_level.txt
politico_toolbox-0.0.8.dist-info/RECORD
