Metadata-Version: 2.1
Name: politico-toolbox
Version: 0.0.8
Summary: Python utilities from POLITICO interactives
Home-page: https://github.com/The-Politico/politico-toolbox
Author: POLITICO interactive news
Author-email: interactives@politico.com
License: MIT
Platform: UNKNOWN
Classifier: Development Status :: 3 - Alpha
Classifier: Intended Audience :: Developers
Classifier: Intended Audience :: Information Technology
Classifier: License :: OSI Approved :: MIT License
Classifier: Operating System :: OS Independent
Classifier: Programming Language :: Python :: 3
Classifier: Programming Language :: Python :: 3.5
Classifier: Programming Language :: Python :: 3.6
Classifier: Topic :: Internet :: WWW/HTTP
Provides-Extra: test
Requires-Dist: pytest ; extra == 'test'
